iteration_utilities/_additional_recipes.py
iteration_utilities/_iteration_utilities.cpython-37m-x86_64-linux-gnu.so
iteration_utilities/_utils.py
iteration_utilities/_classes.py
iteration_utilities/_convenience.py
iteration_utilities/_recipes.py
iteration_utilities/__init__.py
iteration_utilities/_iteration_utilities/seen.c
iteration_utilities/_iteration_utilities/flip.c
iteration_utilities/_iteration_utilities/allequal.c
iteration_utilities/_iteration_utilities/partition.c
iteration_utilities/_iteration_utilities/returnx.c
iteration_utilities/_iteration_utilities/intersperse.h
iteration_utilities/_iteration_utilities/docs_setstate.h
iteration_utilities/_iteration_utilities/docs_reduce.h
iteration_utilities/_iteration_utilities/tabulate.h
iteration_utilities/_iteration_utilities/duplicates.h
iteration_utilities/_iteration_utilities/anyisinstance.h
iteration_utilities/_iteration_utilities/flip.h
iteration_utilities/_iteration_utilities/helper.c
iteration_utilities/_iteration_utilities/placeholder.h
iteration_utilities/_iteration_utilities/dotproduct.h
iteration_utilities/_iteration_utilities/intersperse.c
iteration_utilities/_iteration_utilities/one.h
iteration_utilities/_iteration_utilities/roundrobin.c
iteration_utilities/_iteration_utilities/starfilter.h
iteration_utilities/_iteration_utilities/empty.c
iteration_utilities/_iteration_utilities/helpercompat.h
iteration_utilities/_iteration_utilities/clamp.h
iteration_utilities/_iteration_utilities/minmax.h
iteration_utilities/_iteration_utilities/exported_helper.c
iteration_utilities/_iteration_utilities/groupedby.c
iteration_utilities/_iteration_utilities/chained.h
iteration_utilities/_iteration_utilities/packed.h
iteration_utilities/_iteration_utilities/countitems.h
iteration_utilities/_iteration_utilities/starfilter.c
iteration_utilities/_iteration_utilities/allisinstance.h
iteration_utilities/_iteration_utilities/sideeffect.h
iteration_utilities-0.13.0.dist-info/LICENSE.txt
iteration_utilities-0.13.0.dist-info/METADATA
iteration_utilities-0.13.0.dist-info/RECORD
iteration_utilities-0.13.0.dist-info/WHEEL
iteration_utilities-0.13.0.dist-info/top_level.txt
