Metadata-Version: 2.1
Name: iteration_utilities
Version: 0.13.0
Summary: Utilities based on Pythons iterators and generators.
Author-email: Michael Seifert <michaelseifert04@yahoo.de>
License: Apache License Version 2.0
Project-URL: Homepage, https://github.com/MSeifert04/iteration_utilities
Project-URL: Documentation, https://iteration-utilities.readthedocs.io/en/latest/
Project-URL: Repository, https://github.com/MSeifert04/iteration_utilities.git
Project-URL: Changelog, https://github.com/MSeifert04/iteration_utilities/blob/master/docs/CHANGES.rst
Keywords: functional,functools,generator,itertools,iteration,iterator,operators,performance,reduce,utility
Classifier: Development Status :: 5 - Production/Stable
Classifier: Programming Language :: Python :: 3
Classifier: Programming Language :: Python :: 3.7
Classifier: Programming Language :: Python :: 3.8
Classifier: Programming Language :: Python :: 3.9
Classifier: Programming Language :: Python :: 3.10
Classifier: Programming Language :: Python :: 3.11
Classifier: Programming Language :: Python :: 3.12
Classifier: Programming Language :: Python :: 3.13
Classifier: Operating System :: MacOS :: MacOS X
Classifier: Operating System :: Microsoft :: Windows
Classifier: Operating System :: POSIX :: Linux
Classifier: Programming Language :: Python :: Implementation :: CPython
Classifier: Programming Language :: Python :: Implementation :: PyPy
Classifier: Topic :: Utilities
Requires-Python: >=3.7
License-File: LICENSE.txt
Provides-Extra: test
Requires-Dist: pytest; extra == "test"
Provides-Extra: documentation
Requires-Dist: sphinx>=2.2; extra == "documentation"
Requires-Dist: numpydoc; extra == "documentation"
